Metadata-Version: 1.0
Name: neha-probability-distribution
Version: 1.0
Summary: Gaussian and Binomial distributions
Home-page: UNKNOWN
Author: Neha Kalbande
Author-email: neha.leenaharsh@gmail.com
License: UNKNOWN
Platform: UNKNOWN
